CRO_Tax_Debtors-0.5.1.dist-info/LICENSE.txt
CRO_Tax_Debtors-0.5.1.dist-info/METADATA
CRO_Tax_Debtors-0.5.1.dist-info/RECORD
CRO_Tax_Debtors-0.5.1.dist-info/WHEEL
CRO_Tax_Debtors-0.5.1.dist-info/entry_points.txt
CRO_Tax_Debtors-0.5.1.dist-info/top_level.txt
cro_tax_debtors/__init__.py
cro_tax_debtors/cli.py
cro_tax_debtors/debtors.py
cro_tax_debtors/save_handlers.py
cro_tax_debtors/screen.py
cro_tax_debtors/spiders.py
