Metadata-Version: 2.1
Name: CRO-Tax-Debtors
Version: 0.5.1
Summary: List of Croatian tax debtors
Home-page: https://github.com/arrrlo/CRO-Tax-Debtors
Author: Ivan Arar
Author-email: ivan.arar@gmail.com
License: MIT
Project-URL: Source, https://github.com/arrrlo/CRO-Tax-Debtors
Keywords: croatia,tax,debt
Platform: UNKNOWN
Classifier: Development Status :: 4 - Beta
Classifier: Intended Audience :: Developers
Classifier: Topic :: Software Development :: Build Tools
Classifier: License :: OSI Approved :: MIT License
Classifier: Programming Language :: Python :: 2.7
Classifier: Programming Language :: Python :: 3.6
Requires-Dist: click (~=6.7)
Requires-Dist: colorama (~=0.3)
Requires-Dist: db-transfer (~=0.5.0)
Requires-Dist: requests (~=2.20.0)
Requires-Dist: lxml (==4.2.1)
Requires-Dist: python-slugify (~=1.2.5)
Requires-Dist: pyfiglet (~=0.7.5)
Requires-Dist: termcolor (~=1.1.0)
Requires-Dist: progress (<1.3,>=1.2)
Requires-Dist: six (~=1.11.0)
